jt
setup.py
Jterator.egg-info/PKG-INFO
Jterator.egg-info/SOURCES.txt
Jterator.egg-info/dependency_links.txt
Jterator.egg-info/requires.txt
Jterator.egg-info/top_level.txt
jterator/__init__.py
jterator/error.py
jterator/minify_json.py
jterator/module.py
jterator/runner.py
jterator/utils.py
jterator/api/__init__.py
jterator/api/io.py